Metadata-Version: 2.1
Name: testingadfadf
Version: 4.2.0
Home-page: http://ml-ci.amd.com:21096/view/ZenDNN/job/zendnn/job/tensorflow-zendnn-plugin-build-whl-release/
Download-URL: https://github.com/amd/ZenDNN-tensorflow-plugin
Author: AMD
Author-email: zendnn.maintainers@amd.com
License: Apache 2.0
Keywords: tensorflow tensor machine learning plugin
Classifier: Development Status :: 5 - Production/Stable
Classifier: Intended Audience :: Developers
Classifier: Intended Audience :: Education
Classifier: Intended Audience :: Science/Research
Classifier: License :: OSI Approved :: Apache Software License
Classifier: Programming Language :: Python :: 3
Classifier: Programming Language :: Python :: 3.9
Classifier: Programming Language :: Python :: 3.10
Classifier: Programming Language :: Python :: 3.11
Classifier: Programming Language :: Python :: 3.12
Classifier: Topic :: Scientific/Engineering
Classifier: Topic :: Scientific/Engineering :: Mathematics
Classifier: Topic :: Scientific/Engineering :: Artificial Intelligence
Classifier: Topic :: Software Development
Classifier: Topic :: Software Development :: Libraries
Classifier: Topic :: Software Development :: Libraries :: Python Modules
Requires-Dist: grpcio >=1.8.6
Requires-Dist: wheel >=0.26
